pyyardian/__init__.py
pyyardian/async_client.py
pyyardian/const.py
pyyardian/exceptions.py
pyyardian-1.0.2.dist-info/METADATA
pyyardian-1.0.2.dist-info/WHEEL
pyyardian-1.0.2.dist-info/top_level.txt
pyyardian-1.0.2.dist-info/RECORD
