Metadata-Version: 2.1
Name: pyyardian
Version: 1.0.2
Summary: A module for interacting with the Yardian irrigation controller
Home-page: https://github.com/h3l1o5/pyyardian
Author: Marty Sun
Author-email: marty.sun@aeonmatrix.com
License: MIT
Platform: UNKNOWN
